graphlab_py/GraphLab.py
graphlab_py/__init__.py
graphlab_py-0.1.4.dist-info/LICENSE
graphlab_py-0.1.4.dist-info/METADATA
graphlab_py-0.1.4.dist-info/WHEEL
graphlab_py-0.1.4.dist-info/RECORD
