Metadata-Version: 2.1
Name: graphlab-py
Version: 0.1.4
Summary: 
Author: knutole
Author-email: knutole@graphlab.ai
Requires-Python: >=3.8,<4.0
Classifier: Programming Language :: Python :: 3
Classifier: Programming Language :: Python :: 3.8
Classifier: Programming Language :: Python :: 3.9
Classifier: Programming Language :: Python :: 3.10
Classifier: Programming Language :: Python :: 3.11
Classifier: Programming Language :: Python :: 3.12
Classifier: Programming Language :: Python :: 3.13
Requires-Dist: litellm (>=1.54.1,<2.0.0)
